[
    {
        "id": 1,
        "email": "john@mail.com",
        "nombre": "Jhon"
    },
    {
        "id": 2,
        "email": "maria@mail.com",
        "nombre": "Maria"
    },
    {
        "id": 3,
        "email": "admin@mail.com",
        "nombre": "Admin"
    },
    {
        "id": 4,
        "email": "nosa@mail.com",
        "nombre": "nosa"
    },
    {
        "id": 5,
        "email": "mayar.re2211@gmail.com",
        "nombre": "yura"
    },
    {
        "id": 6,
        "email": "Hugh_Dickens@yahoo.com",
        "nombre": "Jovani.Kuphal"
    },
    {
        "id": 7,
        "email": "beko@gmail.com",
        "nombre": "beko"
    },
    {
        "id": 8,
        "email": "nico@gmail.com",
        "nombre": "Nicolas"
    },
    {
        "id": 9,
        "email": "aaaa@gmail.com",
        "nombre": "aaaa"
    },
    {
        "id": 10,
        "email": "yeheaf@mail.com",
        "nombre": "yehea"
    },
    {
        "id": 11,
        "email": "nico@gmail.com",
        "nombre": "Nicolas"
    },
    {
        "id": 12,
        "email": "fandi@gmail.con",
        "nombre": "yehea"
    }
]